<?xml version="1.0" encoding="UTF-8"?>
<!DOCTYPE hibernate-reverse-engineering PUBLIC "-//Hibernate/Hibernate Reverse Engineering DTD 3.0//EN" "http://hibernate.sourceforge.net/hibernate-reverse-engineering-3.0.dtd">
<hibernate-reverse-engineering>
  <schema-selection match-catalog="inge" match-schema="public"/>
  <table-filter match-name="direccion_usuario"/>
  <table-filter match-name="usuario"/>
  <table-filter match-name="publicacion"/>
  <table-filter match-name="galeria_publicacion"/>
  <table-filter match-name="nombre_usuario"/>
  <table-filter match-name="datos_usuario"/>
  <table-filter match-name="estado"/>
</hibernate-reverse-engineering>
